<?xml version = '1.0' encoding = 'UTF-8'?>
<Relation class="oracle.dbtools.crest.model.design.logical.Relation" name="Pracownicy Miejscowosci FK" directorySegmentName="seg_0" id="5C4732CC-EAB5-D75A-EF20-893C78435BEA">
<createdBy>izara</createdBy>
<createdTime>2024-03-01 09:47:22 UTC</createdTime>
<ownerDesignName>pastry_model</ownerDesignName>
<engineerTo>
<item key="172B2CA0-CAA7-6C7B-9E91-091895813792" value="true"/>
</engineerTo>
<sourcePk>1F08B607-0216-3232-5E11-AAC344FA5A8C</sourcePk>
<identifying>false</identifying>
<optionalSource>true</optionalSource>
<optionalTarget>false</optionalTarget>
<sourceCardinality>1</sourceCardinality>
<sourceEntity>47D1E785-75E8-8751-AD15-498962AFE5B0</sourceEntity>
<targetCardinalityString>*</targetCardinalityString>
<targetEntity>D96F3FB0-1CA1-2258-2B98-0A0138F6AD5C</targetEntity>
<transferable>true</transferable>
<deleteRule>NO ACTION</deleteRule>
</Relation>